Workbook

Sheet README
B1: True* Suite — Unit Economics Model
B3: How to use this model
B4: All blue cells are inputs you can change. Black cells are formulas. Green cells pull from other sheets.
B5: Start on the Assumptions tab — every number flows from there. Change an assumption and the whole model recomputes.
B7: Tabs
B8: Assumptions — every driver in one place (pricing, costs, CAC, churn, adoption, the calendar build-vs-buy toggle).
B9: Per-Unit Economics — CAC / LTV / payback for each product and for the bundle, per paying customer.
B10: Suite P&L (Monthly) — a 24-month projection of customers, revenue, gross margin, and contribution after CAC.
B11: Scenarios — three quick what-if cases (Conservative / Base / Optimistic) on the levers that matter most.
B13: The big modeling decisions baked in
B14: 1. Bundle is the business model. The strategy docs concluded all three products are sold as one bundle; the model treats the bundle as the primary unit and the standalone products as feeders.
B15: 2. CAC is low because distribution is the moat. Most customers come from the existing TrueQR base via cross-sell, not paid acquisition. The blended CAC input reflects that — change it to test the thesis.
... B20: These are planning assumptions, not forecasts. Every input is a guess until validated against the real TrueQR list and live cost data. The model's value is letting you change a guess and immediately see whether the unit economics still work.

Sheet Assumptions
B1: Assumptions — all model drivers
B2: Yellow cells are inputs. Change them to test the model.
B4: A. Pricing (monthly, per paying customer)
B5: TrueQR — standalone Pro | C5: 5 | E5: Existing product baseline price
B6: TruePage — standalone Pro | C6: 12 | E6: Strategy doc: ~$9–12/mo
B7: TrueBook — standalone Pro | C7: 15 | E7: Priced as bundle lever, not standalone max
B8: Bundle (all three) Pro | C8: 24 | E8: Discount vs $32 sum — the core offer
B9: Implied bundle discount | C9: =1-C8/(C5+C6+C7) -> 0.25 | E9: Auto-calculated
B11: B. Variable cost — TruePage (AI generation)
B12: AI cost per page generation | C12: 0.04 | E12: Model call + retry; validate vs provider
B13: Avg generations per customer / mo | C13: 3 | E13: Regens + new pages
B14: Hosting cost per page / mo | C14: 0.3 | E14: Static page hosting + bandwidth
B16: C. Variable cost — TrueBook (calendar + notifications)
B17: Calendar sync: build or buy | C17: buy | E17: Type 'buy' or 'build' — flips cost below
B18: Unified API cost / account / mo (buy) | C18: 0.5 | E18: e.g. Nylas/Cronofy per-account fee
B19: Direct API cost / account / mo (build) | C19: 0.05 | E19: Marginal infra only; eng cost is elsewhere
B20: Effective calendar cost / mo | C20: =IF(C17="build",C19,C18) -> 0.5 | E20: Driven by toggle above
B21: SMS cost per message | C21: 0.01 | E21: Confirmation + reminders
B22: SMS messages per customer / mo | C22: 20 | E22: Bookings x ~2 msgs each
B24: D. Other variable cost (all paying customers)
B25: Payment processing on subscription | C25: 0.029 | E25: Stripe ~2.9% + fixed (fixed omitted)
B26: Support cost / customer / mo | C26: 1.5 | E26: Higher for TrueBook — blended here
B28: E. Acquisition & retention
B29: CAC — cross-sell from TrueQR base | C29: 8 | E29: Email/in-app; the distribution moat
B30: CAC — paid/new acquisition | C30: 45 | E30: SEO + paid; for net-new customers
B31: % of new customers from cross-sell | C31: 0.7 | E31: Thesis: most growth is cheap cross-sell
B32: Blended CAC | C32: =C29*C31+C30*(1-C31) -> 19.1 | E32: Auto-calculated
B33: Monthly churn (bundle) | C33: 0.04 | E33: Bundle stickier than standalone
B34: Monthly churn (standalone) | C34: 0.07 | E34: Single-product customers leave faster
B35: Implied bundle lifetime (months) | C35: =1/C33 -> 25 | E35: 1 / churn
B37: F. Growth (for Suite P&L projection)
B38: Starting paying customers (month 1) | C38: 50 | E38: Initial converts from TrueQR base
B39: New customers added / month | C39: 40 | E39: Gross adds before churn
B40: % of paying customers on bundle | C40: 0.6 | E40: Rest are single/standalone

Sheet Per-Unit Economics
B1: Per-Unit Economics (per paying customer / month)
B3: Metric | C3: TrueQR | D3: TruePage | E3: TrueBook | F3: Bundle | G3: Notes
B4: Monthly revenue | C4: =Assumptions!C5 -> 5 | D4: =Assumptions!C6 -> 12 | E4: =Assumptions!C7 -> 15 | F4: =Assumptions!C8 -> 24 | G4: From Assumptions A
B5: AI generation cost | C5: 0 | D5: =Assumptions!C12*Assumptions!C13 -> 0.12 | E5: 0 | F5: =Assumptions!C12*Assumptions!C13 -> 0.12 | G5: TruePage only
B6: Hosting cost | C6: 0 | D6: =Assumptions!C14 -> 0.3 | E6: 0 | F6: =Assumptions!C14 -> 0.3 | G6: Page hosting
B7: Calendar sync cost | C7: 0 | D7: 0 | E7: =Assumptions!C20 -> 0.5 | F7: =Assumptions!C20 -> 0.5 | G7: TrueBook; driven by build/buy toggle
B8: SMS cost | C8: 0 | D8: 0 | E8: =Assumptions!C21*Assumptions!C22 -> 0.2 | F8: =Assumptions!C21*Assumptions!C22 -> 0.2 | G8: TrueBook notifications
B9: Payment processing | C9: =Assumptions!C5*Assumptions!C25 -> 0.145 | D9: =Assumptions!C6*Assumptions!C25 -> 0.348 | E9: =Assumptions!C7*Assumptions!C25 -> 0.435 | F9: =Assumptions!C8*Assumptions!C25 -> 0.696 | G9: % of revenue
B10: Support cost | C10: =Assumptions!C26 -> 1.5 | D10: =Assumptions!C26 -> 1.5 | E10: =Assumptions!C26 -> 1.5 | F10: =Assumptions!C26 -> 1.5 | G10: Blended; TrueBook heavier in reality
B11: Total variable cost | C11: =SUM(C5:C10) -> 1.645 | D11: =SUM(D5:D10) -> 2.268 | E11: =SUM(E5:E10) -> 2.635 | F11: =SUM(F5:F10) -> 3.316
B12: Gross profit / mo | C12: =C4-C11 -> 3.355 | D12: =D4-D11 -> 9.732 | E12: =E4-E11 -> 12.365 | F12: =F4-F11 -> 20.684
B13: Gross margin % | C13: =IF(C4=0,0,C12/C4) -> 0.671 | D13: =IF(D4=0,0,D12/D4) -> 0.811 | E13: =IF(E4=0,0,E12/E4) -> 0.82433333 | F13: =IF(F4=0,0,F12/F4) -> 0.86183333
B15: LTV / CAC (bundle-focused)
B16: Customer lifetime (months) | C16: =1/Assumptions!C34 -> 14.285714 | D16: =1/Assumptions!C34 -> 14.285714 | E16: =1/Assumptions!C34 -> 14.285714 | F16: =1/Assumptions!C33 -> 25 | G16: Bundle churn is lower (stickier)
B17: LTV (gross profit basis) | C17: =C12*C16 -> 47.928571 | D17: =D12*D16 -> 139.02857 | E17: =E12*E16 -> 176.64286 | F17: =F12*F16 -> 517.1
B18: CAC (blended) | C18: =Assumptions!C32 -> 19.1 | D18: =Assumptions!C32 -> 19.1 | E18: =Assumptions!C32 -> 19.1 | F18: =Assumptions!C32 -> 19.1
B19: LTV : CAC ratio | C19: =IF(C18=0,0,C17/C18) -> 2.5093493 | D19: =IF(D18=0,0,D17/D18) -> 7.2789828 | E19: =IF(E18=0,0,E17/E18) -> 9.2483171 | F19: =IF(F18=0,0,F17/F18) -> 27.073298
B20: CAC payback (months) | C20: =IF(C12=0,0,C18/C12) -> 5.6929955 | D20: =IF(D12=0,0,D18/D12) -> 1.9625976 | E20: =IF(E12=0,0,E18/E12) -> 1.5446826 | F20: =IF(F12=0,0,F18/F12) -> 0.92341907
B21: Note: LTV:CAC above ~3.0x is the standard health benchmark; payback under ~12 months is strong.

Sheet Suite P&L (Monthly)
B1: Suite P&L — 24-Month Projection
B3: Month | C3: 1 | D3: 2 | E3: 3 | F3: 4 | G3: 5 | H3: 6 | I3: 7 | J3: 8 | K3: 9 | L3: 10 | M3: 11 | N3: 12 | O3: 13 | P3: 14 | Q3: 15 | R3: 16 | S3: 17 | T3: 18 | U3: 19 | V3: 20 | W3: 21 | X3: 22 | Y3: 23 | Z3: 24
B4: Customers
B5: Beginning customers | C5: 0 | D5: =C8 -> 50 | E5: =D8 -> 88 | F5: =E8 -> 124.48 | G5: =F8 -> 159.5008 | H5: =G8 -> 193.12077 | I5: =H8 -> 225.39594 | J5: =I8 -> 256.3801 | K5: =J8 -> 286.1249 | ... Z5: =Y8 -> 613.01803
B6: New customers | C6: =Assumptions!C38 -> 50 | D6: =Assumptions!C39 -> 40 | E6: =Assumptions!C39 -> 40 | F6: =Assumptions!C39 -> 40 | G6: =Assumptions!C39 -> 40 | H6: =Assumptions!C39 -> 40 | I6: =Assumptions!C39 -> 40 | J6: =Assumptions!C39 -> 40 | K6: =Assumptions!C39 -> 40 | L6: =Assumptions!C39 -> 40 | M6: =Assumptions!C39 -> 40 | N6: =Assumptions!C39 -> 40 | O6: =Assumptions!C39 -> 40 | P6: =Assumptions!C39 -> 40 | Q6: =Assumptions!C39 -> 40 | R6: =Assumptions!C39 -> 40 | S6: =Assumptions!C39 -> 40 | T6: =Assumptions!C39 -> 40 | U6: =Assumptions!C39 -> 40 | V6: =Assumptions!C39 -> 40 | W6: =Assumptions!C39 -> 40 | X6: =Assumptions!C39 -> 40 | Y6: =Assumptions!C39 -> 40 | Z6: =Assumptions!C39 -> 40
B7: Churned customers | C7: =-C5*Assumptions!C33 -> 0 | D7: =-D5*Assumptions!C33 -> -2 | E7: =-E5*Assumptions!C33 -> -3.52 | F7: =-F5*Assumptions!C33 -> -4.9792 | G7: =-G5*Assumptions!C33 -> -6.380032 | H7: =-H5*Assumptions!C33 -> -7.7248307 | I7: =-I5*Assumptions!C33 -> -9.0158375 | J7: =-J5*Assumptions!C33 -> -10.255204 | K7: =-K5*Assumptions!C33 -> -11.444996 | L7: =-L5*Assumptions!C33 -> -12.587196 | M7: =-M5*Assumptions!C33 -> -13.683708 | N7: =-N5*Assumptions!C33 -> -14.73636 | O7: =-O5*Assumptions!C33 -> -15.746905 | P7: =-P5*Assumptions!C33 -> -16.717029 | Q7: =-Q5*Assumptions!C33 -> -17.648348 | R7: =-R5*Assumptions!C33 -> -18.542414 | S7: =-S5*Assumptions!C33 -> -19.400718 | T7: =-T5*Assumptions!C33 -> -20.224689 | U7: =-U5*Assumptions!C33 -> -21.015701 | V7: =-V5*Assumptions!C33 -> -21.775073 | W7: =-W5*Assumptions!C33 -> -22.50407 | X7: =-X5*Assumptions!C33 -> -23.203908 | Y7: =-Y5*Assumptions!C33 -> -23.875751 | Z7: =-Z5*Assumptions!C33 -> -24.520721
B8: Ending customers | C8: =C5+C6+C7 -> 50 | D8: =D5+D6+D7 -> 88 | E8: =E5+E6+E7 -> 124.48 | F8: =F5+F6+F7 -> 159.5008 | G8: =G5+G6+G7 -> 193.12077 | H8: =H5+H6+H7 -> 225.39594 | I8: =I5+I6+I7 -> 256.3801 | J8: =J5+J6+J7 -> 286.1249 | ... Z8: =Z5+Z6+Z7 -> 628.49731
B10: Revenue & Margin
B11: Blended revenue / customer | C11: =Assumptions!C40*Assumptions!C8+(1-Assumptions!C40)*Assumptions!C6 -> 19.2 | D11: =Assumptions!C40*Assumptions!C8+(1-Assumptions!C40)*Assumptions!C6 -> 19.2 | E11: =Assumptions!C40*Assumptions!C8+(1-Assumptions!C40)*Assumptions!C6 -> 19.2 | F11: =Assumptions!C40*Assumptions!C8+(1-Assumptions!C40)*Assumptions!C6 -> 19.2 | G11: =Assumptions!C40*Assumptions!C8+(1-Assumptions!C40)*Assumptions!C6 -> 19.2 | H11: =Assumptions!C40*Assumptions!C8+(1-Assumptions!C40)*Assumptions!C6 -> 19.2 | I11: =Assumptions!C40*Assumptions!C8+(1-Assumptions!C40)*Assumptions!C6 -> 19.2 | J11: =Assumptions!C40*Assumptions!C8+(1-Assumptions!C40)*Assumptions!C6 -> 19.2 | K11: =Assumptions!C40*Assumptions!C8+(1-Assumptions!C40)*Assumptions!C6 -> 19.2 | L11: =Assumptions!C40*Assumptions!C8+(1-Assumptions!C40)*Assumptions!C6 -> 19.2 | M11: =Assumptions!C40*Assumptions!C8+(1-Assumptions!C40)*Assumptions!C6 -> 19.2 | N11: =Assumptions!C40*Assumptions!C8+(1-Assumptions!C40)*Assumptions!C6 -> 19.2 | O11: =Assumptions!C40*Assumptions!C8+(1-Assumptions!C40)*Assumptions!C6 -> 19.2 | P11: =Assumptions!C40*Assumptions!C8+(1-Assumptions!C40)*Assumptions!C6 -> 19.2 | Q11: =Assumptions!C40*Assumptions!C8+(1-Assumptions!C40)*Assumptions!C6 -> 19.2 | R11: =Assumptions!C40*Assumptions!C8+(1-Assumptions!C40)*Assumptions!C6 -> 19.2 | S11: =Assumptions!C40*Assumptions!C8+(1-Assumptions!C40)*Assumptions!C6 -> 19.2 | T11: =Assumptions!C40*Assumptions!C8+(1-Assumptions!C40)*Assumptions!C6 -> 19.2 | U11: =Assumptions!C40*Assumptions!C8+(1-Assumptions!C40)*Assumptions!C6 -> 19.2 | V11: =Assumptions!C40*Assumptions!C8+(1-Assumptions!C40)*Assumptions!C6 -> 19.2 | W11: =Assumptions!C40*Assumptions!C8+(1-Assumptions!C40)*Assumptions!C6 -> 19.2 | X11: =Assumptions!C40*Assumptions!C8+(1-Assumptions!C40)*Assumptions!C6 -> 19.2 | Y11: =Assumptions!C40*Assumptions!C8+(1-Assumptions!C40)*Assumptions!C6 -> 19.2 | Z11: =Assumptions!C40*Assumptions!C8+(1-Assumptions!C40)*Assumptions!C6 -> 19.2
B12: Total revenue | C12: =C8*C11 -> 960 | D12: =D8*D11 -> 1689.6 | E12: =E8*E11 -> 2390.016 | F12: =F8*F11 -> 3062.4154 | G12: =G8*G11 -> 3707.9187 | H12: =H8*H11 -> 4327.602 | I12: =I8*I11 -> 4922.4979 | J12: =J8*J11 -> 5493.598 | ... Z12: =Z8*Z11 -> 12067.148
B13: Blended GM % | C13: ='Per-Unit Economics'!F13 -> 0.86183333 | D13: ='Per-Unit Economics'!F13 -> 0.86183333 | E13: ='Per-Unit Economics'!F13 -> 0.86183333 | F13: ='Per-Unit Economics'!F13 -> 0.86183333 | G13: ='Per-Unit Economics'!F13 -> 0.86183333 | H13: ='Per-Unit Economics'!F13 -> 0.86183333 | I13: ='Per-Unit Economics'!F13 -> 0.86183333 | J13: ='Per-Unit Economics'!F13 -> 0.86183333 | K13: ='Per-Unit Economics'!F13 -> 0.86183333 | L13: ='Per-Unit Economics'!F13 -> 0.86183333 | M13: ='Per-Unit Economics'!F13 -> 0.86183333 | N13: ='Per-Unit Economics'!F13 -> 0.86183333 | O13: ='Per-Unit Economics'!F13 -> 0.86183333 | P13: ='Per-Unit Economics'!F13 -> 0.86183333 | Q13: ='Per-Unit Economics'!F13 -> 0.86183333 | R13: ='Per-Unit Economics'!F13 -> 0.86183333 | S13: ='Per-Unit Economics'!F13 -> 0.86183333 | T13: ='Per-Unit Economics'!F13 -> 0.86183333 | U13: ='Per-Unit Economics'!F13 -> 0.86183333 | V13: ='Per-Unit Economics'!F13 -> 0.86183333 | W13: ='Per-Unit Economics'!F13 -> 0.86183333 | X13: ='Per-Unit Economics'!F13 -> 0.86183333 | Y13: ='Per-Unit Economics'!F13 -> 0.86183333 | Z13: ='Per-Unit Economics'!F13 -> 0.86183333
B14: Gross profit | C14: =C12*C13 -> 827.36 | D14: =D12*D13 -> 1456.1536 | E14: =E12*E13 -> 2059.7955 | F14: =F12*F13 -> 2639.2916 | G14: =G12*G13 -> 3195.608 | H14: =H12*H13 -> 3729.6717 | I14: =I12*I13 -> 4242.3728 | J14: =J12*J13 -> 4734.5659 | ... Z14: =Z12*Z13 -> 10399.871
B16: Acquisition & Contribution
B17: CAC spend (this month's adds) | C17: =-C6*Assumptions!C32 -> -955 | D17: =-D6*Assumptions!C32 -> -764 | E17: =-E6*Assumptions!C32 -> -764 | F17: =-F6*Assumptions!C32 -> -764 | G17: =-G6*Assumptions!C32 -> -764 | H17: =-H6*Assumptions!C32 -> -764 | I17: =-I6*Assumptions!C32 -> -764 | J17: =-J6*Assumptions!C32 -> -764 | K17: =-K6*Assumptions!C32 -> -764 | L17: =-L6*Assumptions!C32 -> -764 | M17: =-M6*Assumptions!C32 -> -764 | N17: =-N6*Assumptions!C32 -> -764 | O17: =-O6*Assumptions!C32 -> -764 | P17: =-P6*Assumptions!C32 -> -764 | Q17: =-Q6*Assumptions!C32 -> -764 | R17: =-R6*Assumptions!C32 -> -764 | S17: =-S6*Assumptions!C32 -> -764 | T17: =-T6*Assumptions!C32 -> -764 | U17: =-U6*Assumptions!C32 -> -764 | V17: =-V6*Assumptions!C32 -> -764 | W17: =-W6*Assumptions!C32 -> -764 | X17: =-X6*Assumptions!C32 -> -764 | Y17: =-Y6*Assumptions!C32 -> -764 | Z17: =-Z6*Assumptions!C32 -> -764
B18: Contribution after CAC | C18: =C14+C17 -> -127.64 | D18: =D14+D17 -> 692.1536 | E18: =E14+E17 -> 1295.7955 | F18: =F14+F17 -> 1875.2916 | G18: =G14+G17 -> 2431.608 | H18: =H14+H17 -> 2965.6717 | I18: =I14+I17 -> 3478.3728 | J18: =J14+J17 -> 3970.5659 | ... Z18: =Z14+Z17 -> 9635.8707
B19: Cumulative contribution | C19: =C18 -> -127.64 | D19: =C19+D18 -> 564.5136 | E19: =D19+E18 -> 1860.3091 | F19: =E19+F18 -> 3735.6007 | G19: =F19+G18 -> 6167.2087 | H19: =G19+H18 -> 9132.8803 | I19: =H19+I18 -> 12611.253 | J19: =I19+J18 -> 16581.819 | K19: =J19+K18 -> 21024.89 | ... Z19: =Y19+Z18 -> 133145.7
B21: Note: month 1 'new' uses starting-customers input; months 2+ use monthly adds. Churn applies to beginning balance.

Sheet Scenarios
B1: Scenarios — key levers
B3: These are reference scenarios. Set the Assumptions tab to one of these columns to see full output.
B5: Lever | C5: Conservative | D5: Base | E5: Optimistic | F5: Comment
B6: Bundle price ($/mo) | C6: 20 | D6: 24 | E6: 29 | F6: Higher price tests willingness to pay
B7: % new from cross-sell | C7: 0.5 | D7: 0.7 | E7: 0.85 | F7: Core thesis: cheap distribution
B8: Monthly churn (bundle) | C8: 0.06 | D8: 0.04 | E8: 0.025 | F8: Stickiness of the loop
B9: New customers / month | C9: 25 | D9: 40 | E9: 75 | F9: Velocity of cross-sell + SEO
B10: Calendar cost / acct (buy) | C10: 0.5 | D10: 0.5 | E10: 0.35 | F10: Vendor negotiation upside
B11: % on bundle | C11: 0.45 | D11: 0.6 | E11: 0.75 | F11: Attach rate of full suite
